tests/fixtures/__init__.py
tests/fixtures/multiple_sample_rate_fixture.py
tests/helpers/__init__.py
tests/helpers/json_reader.py
time_series_generator/__init__.py
time_series_generator/time_series_generator.py
time_series_generator-0.2.8.dist-info/LICENSE
time_series_generator-0.2.8.dist-info/METADATA
time_series_generator-0.2.8.dist-info/WHEEL
time_series_generator-0.2.8.dist-info/top_level.txt
time_series_generator-0.2.8.dist-info/RECORD
