Metadata-Version: 2.1
Name: time-series-generator
Version: 0.2.8
Summary: Time Series Generator
Home-page: https://time-series-generator.readthedocs.io/en/latest/
Author: Daniel Kaminski de Souza
Author-email: daniel@kryptonunite.com
License: UNKNOWN
Platform: UNKNOWN
Classifier: Programming Language :: Python :: 3
Classifier: License :: OSI Approved :: GNU General Public License v3 (GPLv3)
Classifier: Operating System :: OS Independent
Requires-Python: >=3.6
Requires-Dist: numpy
Provides-Extra: dev
Requires-Dist: autopep8 ; extra == 'dev'
Requires-Dist: bumpversion ; extra == 'dev'
Requires-Dist: pylint ; extra == 'dev'
Requires-Dist: rstcheck ; extra == 'dev'
Requires-Dist: twine ; extra == 'dev'
Requires-Dist: wheel ; extra == 'dev'
Provides-Extra: docs
Requires-Dist: IPython ; extra == 'docs'
Requires-Dist: docutils ; extra == 'docs'
Requires-Dist: ipykernel ; extra == 'docs'
Requires-Dist: nbsphinx ; extra == 'docs'
Requires-Dist: recommonmark ; extra == 'docs'
Requires-Dist: sphinx ; extra == 'docs'
Requires-Dist: sphinx-autobuild ; extra == 'docs'
Requires-Dist: sphinx-autodoc-typehints ; extra == 'docs'
Requires-Dist: sphinx-rtd-theme ; extra == 'docs'
Requires-Dist: sphinxcontrib-svg2pdfconverter ; extra == 'docs'
Provides-Extra: test
Requires-Dist: pytest-cov ; extra == 'test'
Requires-Dist: pytest (>=4.6) ; extra == 'test'
Requires-Dist: tensorflow ; extra == 'test'
